[
    {
        "Id": 6001,
        "Name": "통나무",
        "Value": 1,
        "ItemType": "FUEL",
        "ItemProperty": "MATERIAL",
        "FuelData": {
            "BurnPower": 10
        },
        "MaterialData": {
            "GrindCount": 1,
            "Type": "WOOD"
        }
    },
    {
        "Id": 6002,
        "Name": "석탄",
        "Value": 2,
        "ItemType": "FUEL",
        "ItemProperty": "NONE",
        "FuelData": {
            "BurnPower": 20
        }
    },
    {
        "Id": 6101,
        "Name": "볼트",
        "Value": 1,
        "ItemType": "MATERIAL",
        "ItemProperty": "MATERIAL",
        "MaterialData": {
            "GrindCount": 1,
            "Type": "IRON"
        }
    },
    {
        "Id": 6102,
        "Name": "낡은 라디오",
        "Value": 2,
        "ItemType": "MATERIAL",
        "ItemProperty": "MATERIAL",
        "MaterialData": {
            "GrindCount": 3,
            "Type": "IRON"
        }
    },
    {
        "Id": 6201,
        "Name": "스테이크",
        "Value": 1,
        "ItemType": "FOOD",
        "ItemProperty": "COOKABLE",
        "FoodData": {
            "HungerAmount": 20,
            "HpAmount": 0,
            "NeedCook": true
        }
    },
    {
        "Id": 6202,
        "Name": "케이크",
        "Value": 2,
        "ItemType": "FOOD",
        "ItemProperty": "NONE",
        "FoodData": {
            "HungerAmount": 15,
            "HpAmount": 15,
            "NeedCook": false
        }
    },
    {
        "Id": 6301,
        "Name": "리볼버 탄약",
        "Value": 0,
        "ItemType": "AMMO",
        "ItemProperty": "NONE",
        "AmmoData": {
            "AmmoType": "REVOLVER",
            "Amount": 6
        }
    },
    {
        "Id": 6302,
        "Name": "소총 탄약",
        "Value": 0,
        "ItemType": "AMMO",
        "ItemProperty": "NONE",
        "AmmoData": {
            "AmmoType": "RIFLE",
            "Amount": 6
        }
    }
]